{"config":{"output_file":null,"full_docs":false,"pub_only":false,"reachable_only":false,"distro_crate":false,"signatures":false,"borrow_data":false},"version":"0.19.0","compilation":{"directory":"/home/pi/Rust/section5/vectors","program":"/home/pi/.rustup/toolchains/stable-armv7-unknown-linux-gnueabihf/bin/rls","arguments":[],"output":"/home/pi/Rust/section5/vectors/target/rls/debug/deps/libvectors-9ec57860ae3851af.rmeta"},"prelude":{"crate_id":{"name":"vectors","disambiguator":[18047500128842269648,5142064754964538000]},"crate_root":"src","external_crates":[{"file_name":"/home/pi/Rust/section5/vectors/src/main.rs","num":1,"id":{"name":"std","disambiguator":[1509109216553578296,9633601217011906897]}},{"file_name":"/home/pi/Rust/section5/vectors/src/main.rs","num":2,"id":{"name":"core","disambiguator":[17766026788731291371,15157202272838490464]}},{"file_name":"/home/pi/Rust/section5/vectors/src/main.rs","num":3,"id":{"name":"compiler_builtins","disambiguator":[2181080224676737563,4113177223235881179]}},{"file_name":"/home/pi/Rust/section5/vectors/src/main.rs","num":4,"id":{"name":"rustc_std_workspace_core","disambiguator":[66203773668413857,4818177660075880513]}},{"file_name":"/home/pi/Rust/section5/vectors/src/main.rs","num":5,"id":{"name":"alloc","disambiguator":[10964125668675280051,703726673189641637]}},{"file_name":"/home/pi/Rust/section5/vectors/src/main.rs","num":6,"id":{"name":"libc","disambiguator":[3865279522212986022,11595349660395697871]}},{"file_name":"/home/pi/Rust/section5/vectors/src/main.rs","num":7,"id":{"name":"unwind","disambiguator":[1742437709010394517,6481264401912635320]}},{"file_name":"/home/pi/Rust/section5/vectors/src/main.rs","num":8,"id":{"name":"cfg_if","disambiguator":[11571223140038822310,9295034313938724019]}},{"file_name":"/home/pi/Rust/section5/vectors/src/main.rs","num":9,"id":{"name":"hashbrown","disambiguator":[7182647271116727975,9142010768709207251]}},{"file_name":"/home/pi/Rust/section5/vectors/src/main.rs","num":10,"id":{"name":"rustc_std_workspace_alloc","disambiguator":[15232982032510732065,9939635780388135513]}},{"file_name":"/home/pi/Rust/section5/vectors/src/main.rs","num":11,"id":{"name":"rustc_demangle","disambiguator":[12500967224700115315,7443841378598047075]}},{"file_name":"/home/pi/Rust/section5/vectors/src/main.rs","num":12,"id":{"name":"addr2line","disambiguator":[10211929103405500251,12021531093033342055]}},{"file_name":"/home/pi/Rust/section5/vectors/src/main.rs","num":13,"id":{"name":"gimli","disambiguator":[2220161234607468620,9993424033093637020]}},{"file_name":"/home/pi/Rust/section5/vectors/src/main.rs","num":14,"id":{"name":"object","disambiguator":[15531180943010156133,16233430065945210717]}},{"file_name":"/home/pi/Rust/section5/vectors/src/main.rs","num":15,"id":{"name":"miniz_oxide","disambiguator":[5359670520499159018,15232601530099756558]}},{"file_name":"/home/pi/Rust/section5/vectors/src/main.rs","num":16,"id":{"name":"adler","disambiguator":[16330492945485758846,6206491193234561656]}},{"file_name":"/home/pi/Rust/section5/vectors/src/main.rs","num":17,"id":{"name":"panic_unwind","disambiguator":[11420702146466949069,2051332114452805730]}}],"span":{"file_name":"src/main.rs","byte_start":153,"byte_end":1031,"line_start":7,"line_end":45,"column_start":1,"column_end":2}},"imports":[],"defs":[{"kind":"Mod","id":{"krate":0,"index":0},"span":{"file_name":"src/main.rs","byte_start":153,"byte_end":1031,"line_start":7,"line_end":45,"column_start":1,"column_end":2},"name":"","qualname":"::","value":"src/main.rs","parent":null,"children":[{"krate":0,"index":1},{"krate":0,"index":2},{"krate":0,"index":3},{"krate":0,"index":4}],"decl_id":null,"docs":"","sig":null,"attributes":[]},{"kind":"Function","id":{"krate":0,"index":3},"span":{"file_name":"src/main.rs","byte_start":156,"byte_end":163,"line_start":7,"line_end":7,"column_start":4,"column_end":11},"name":"vectors","qualname":"::vectors","value":"fn vectors()","parent":null,"children":[],"decl_id":null,"docs":"","sig":null,"attributes":[]},{"kind":"Local","id":{"krate":0,"index":3758096387},"span":{"file_name":"src/main.rs","byte_start":179,"byte_end":180,"line_start":8,"line_end":8,"column_start":13,"column_end":14},"name":"a","qualname":"a$HirId { owner: DefId(0:3 ~ vectors[fa75]::vectors), local_id: 7 }","value":"std::vec::Vec<i32>","parent":null,"children":[],"decl_id":null,"docs":"","sig":null,"attributes":[]},{"kind":"Local","id":{"krate":0,"index":2164260867},"span":{"file_name":"src/main.rs","byte_start":321,"byte_end":324,"line_start":16,"line_end":16,"column_start":9,"column_end":12},"name":"idx","qualname":"idx$HirId { owner: DefId(0:3 ~ vectors[fa75]::vectors), local_id: 129 }","value":"usize","parent":null,"children":[],"decl_id":null,"docs":"","sig":null,"attributes":[]},{"kind":"Local","id":{"krate":0,"index":1124073475},"span":{"file_name":"src/main.rs","byte_start":599,"byte_end":601,"line_start":23,"line_end":23,"column_start":14,"column_end":16},"name":"_x","qualname":"_x$HirId { owner: DefId(0:3 ~ vectors[fa75]::vectors), local_id: 194 }","value":"&i32","parent":null,"children":[],"decl_id":null,"docs":"","sig":null,"attributes":[]},{"kind":"Local","id":{"krate":0,"index":75497475},"span":{"file_name":"src/main.rs","byte_start":753,"byte_end":755,"line_start":28,"line_end":28,"column_start":14,"column_end":16},"name":"iter","qualname":"iter$HirId { owner: DefId(0:3 ~ vectors[fa75]::vectors), local_id: 288 }","value":"std::slice::Iter<i32>","parent":null,"children":[],"decl_id":null,"docs":"","sig":null,"attributes":[]},{"kind":"Local","id":{"krate":0,"index":679477251},"span":{"file_name":"src/main.rs","byte_start":753,"byte_end":755,"line_start":28,"line_end":28,"column_start":14,"column_end":16},"name":"__next","qualname":"__next$HirId { owner: DefId(0:3 ~ vectors[fa75]::vectors), local_id: 276 }","value":"&i32","parent":null,"children":[],"decl_id":null,"docs":"","sig":null,"attributes":[]},{"kind":"Local","id":{"krate":0,"index":2826960899},"span":{"file_name":"src/main.rs","byte_start":748,"byte_end":749,"line_start":28,"line_end":28,"column_start":9,"column_end":10},"name":"val","qualname":"val$HirId { owner: DefId(0:3 ~ vectors[fa75]::vectors), local_id: 277 }","value":"&i32","parent":null,"children":[],"decl_id":null,"docs":"","sig":null,"attributes":[]},{"kind":"Local","id":{"krate":0,"index":1417674755},"span":{"file_name":"src/main.rs","byte_start":748,"byte_end":749,"line_start":28,"line_end":28,"column_start":9,"column_end":10},"name":"x","qualname":"x$HirId { owner: DefId(0:3 ~ vectors[fa75]::vectors), local_id: 298 }","value":"&i32","parent":null,"children":[],"decl_id":null,"docs":"","sig":null,"attributes":[]},{"kind":"Local","id":{"krate":0,"index":1451229187},"span":{"file_name":"src/main.rs","byte_start":861,"byte_end":862,"line_start":34,"line_end":34,"column_start":9,"column_end":10},"name":"x","qualname":"x$HirId { owner: DefId(0:3 ~ vectors[fa75]::vectors), local_id: 362 }","value":"std::option::Option<i32>","parent":null,"children":[],"decl_id":null,"docs":"","sig":null,"attributes":[]},{"kind":"Local","id":{"krate":0,"index":3984588803},"span":{"file_name":"src/main.rs","byte_start":951,"byte_end":952,"line_start":37,"line_end":37,"column_start":20,"column_end":21},"name":"x","qualname":"x$HirId { owner: DefId(0:3 ~ vectors[fa75]::vectors), local_id: 439 }","value":"i32","parent":null,"children":[],"decl_id":null,"docs":"","sig":null,"attributes":[]},{"kind":"Function","id":{"krate":0,"index":4},"span":{"file_name":"src/main.rs","byte_start":1008,"byte_end":1012,"line_start":43,"line_end":43,"column_start":4,"column_end":8},"name":"main","qualname":"::main","value":"fn main()","parent":null,"children":[],"decl_id":null,"docs":"","sig":null,"attributes":[]}],"impls":[],"refs":[{"kind":"Function","span":{"file_name":"src/main.rs","byte_start":188,"byte_end":191,"line_start":8,"line_end":8,"column_start":22,"column_end":25},"ref_id":{"krate":5,"index":4848}},{"kind":"Type","span":{"file_name":"src/main.rs","byte_start":183,"byte_end":186,"line_start":8,"line_end":8,"column_start":17,"column_end":20},"ref_id":{"krate":5,"index":4841}},{"kind":"Function","span":{"file_name":"src/main.rs","byte_start":201,"byte_end":205,"line_start":9,"line_end":9,"column_start":7,"column_end":11},"ref_id":{"krate":5,"index":4888}},{"kind":"Variable","span":{"file_name":"src/main.rs","byte_start":199,"byte_end":200,"line_start":9,"line_end":9,"column_start":5,"column_end":6},"ref_id":{"krate":0,"index":3758096387}},{"kind":"Function","span":{"file_name":"src/main.rs","byte_start":216,"byte_end":220,"line_start":10,"line_end":10,"column_start":7,"column_end":11},"ref_id":{"krate":5,"index":4888}},{"kind":"Variable","span":{"file_name":"src/main.rs","byte_start":214,"byte_end":215,"line_start":10,"line_end":10,"column_start":5,"column_end":6},"ref_id":{"krate":0,"index":3758096387}},{"kind":"Function","span":{"file_name":"src/main.rs","byte_start":231,"byte_end":235,"line_start":11,"line_end":11,"column_start":7,"column_end":11},"ref_id":{"krate":5,"index":4888}},{"kind":"Variable","span":{"file_name":"src/main.rs","byte_start":229,"byte_end":230,"line_start":11,"line_end":11,"column_start":5,"column_end":6},"ref_id":{"krate":0,"index":3758096387}},{"kind":"Function","span":{"file_name":"/home/pi/.rustup/toolchains/stable-armv7-unknown-linux-gnueabihf/lib/rustlib/src/rust/library/std/src/macros.rs","byte_start":24731,"byte_end":24764,"line_start":96,"line_end":96,"column_start":28,"column_end":61},"ref_id":{"krate":2,"index":6827}},{"kind":"Variable","span":{"file_name":"src/main.rs","byte_start":264,"byte_end":265,"line_start":12,"line_end":12,"column_start":25,"column_end":26},"ref_id":{"krate":0,"index":3758096387}},{"kind":"Function","span":{"file_name":"/home/pi/.rustup/toolchains/stable-armv7-unknown-linux-gnueabihf/lib/rustlib/src/rust/library/std/src/macros.rs","byte_start":24731,"byte_end":24764,"line_start":96,"line_end":96,"column_start":28,"column_end":61},"ref_id":{"krate":2,"index":6820}},{"kind":"Function","span":{"file_name":"src/main.rs","byte_start":274,"byte_end":278,"line_start":13,"line_end":13,"column_start":7,"column_end":11},"ref_id":{"krate":5,"index":4888}},{"kind":"Variable","span":{"file_name":"src/main.rs","byte_start":272,"byte_end":273,"line_start":13,"line_end":13,"column_start":5,"column_end":6},"ref_id":{"krate":0,"index":3758096387}},{"kind":"Function","span":{"file_name":"/home/pi/.rustup/toolchains/stable-armv7-unknown-linux-gnueabihf/lib/rustlib/src/rust/library/std/src/macros.rs","byte_start":24731,"byte_end":24764,"line_start":96,"line_end":96,"column_start":28,"column_end":61},"ref_id":{"krate":2,"index":6827}},{"kind":"Variable","span":{"file_name":"src/main.rs","byte_start":308,"byte_end":309,"line_start":14,"line_end":14,"column_start":25,"column_end":26},"ref_id":{"krate":0,"index":3758096387}},{"kind":"Function","span":{"file_name":"/home/pi/.rustup/toolchains/stable-armv7-unknown-linux-gnueabihf/lib/rustlib/src/rust/library/std/src/macros.rs","byte_start":24731,"byte_end":24764,"line_start":96,"line_end":96,"column_start":28,"column_end":61},"ref_id":{"krate":2,"index":6820}},{"kind":"Variable","span":{"file_name":"src/main.rs","byte_start":405,"byte_end":406,"line_start":17,"line_end":17,"column_start":5,"column_end":6},"ref_id":{"krate":0,"index":3758096387}},{"kind":"Variable","span":{"file_name":"src/main.rs","byte_start":407,"byte_end":410,"line_start":17,"line_end":17,"column_start":7,"column_end":10},"ref_id":{"krate":0,"index":2164260867}},{"kind":"Function","span":{"file_name":"/home/pi/.rustup/toolchains/stable-armv7-unknown-linux-gnueabihf/lib/rustlib/src/rust/library/std/src/macros.rs","byte_start":24731,"byte_end":24764,"line_start":96,"line_end":96,"column_start":28,"column_end":61},"ref_id":{"krate":2,"index":6827}},{"kind":"Variable","span":{"file_name":"src/main.rs","byte_start":444,"byte_end":445,"line_start":18,"line_end":18,"column_start":26,"column_end":27},"ref_id":{"krate":0,"index":3758096387}},{"kind":"Variable","span":{"file_name":"src/main.rs","byte_start":446,"byte_end":449,"line_start":18,"line_end":18,"column_start":28,"column_end":31},"ref_id":{"krate":0,"index":2164260867}},{"kind":"Function","span":{"file_name":"/home/pi/.rustup/toolchains/stable-armv7-unknown-linux-gnueabihf/lib/rustlib/src/rust/library/std/src/macros.rs","byte_start":24731,"byte_end":24764,"line_start":96,"line_end":96,"column_start":28,"column_end":61},"ref_id":{"krate":2,"index":6820}},{"kind":"Function","span":{"file_name":"src/main.rs","byte_start":513,"byte_end":516,"line_start":21,"line_end":21,"column_start":13,"column_end":16},"ref_id":{"krate":2,"index":8298}},{"kind":"Variable","span":{"file_name":"src/main.rs","byte_start":511,"byte_end":512,"line_start":21,"line_end":21,"column_start":11,"column_end":12},"ref_id":{"krate":0,"index":3758096387}},{"kind":"Type","span":{"file_name":"src/main.rs","byte_start":594,"byte_end":598,"line_start":23,"line_end":23,"column_start":9,"column_end":13},"ref_id":{"krate":2,"index":29814}},{"kind":"Type","span":{"file_name":"src/main.rs","byte_start":594,"byte_end":598,"line_start":23,"line_end":23,"column_start":9,"column_end":13},"ref_id":{"krate":2,"index":29814}},{"kind":"Function","span":{"file_name":"/home/pi/.rustup/toolchains/stable-armv7-unknown-linux-gnueabihf/lib/rustlib/src/rust/library/std/src/macros.rs","byte_start":24731,"byte_end":24764,"line_start":96,"line_end":96,"column_start":28,"column_end":61},"ref_id":{"krate":2,"index":6827}},{"kind":"Variable","span":{"file_name":"src/main.rs","byte_start":639,"byte_end":640,"line_start":23,"line_end":23,"column_start":54,"column_end":55},"ref_id":{"krate":0,"index":3758096387}},{"kind":"Function","span":{"file_name":"/home/pi/.rustup/toolchains/stable-armv7-unknown-linux-gnueabihf/lib/rustlib/src/rust/library/std/src/macros.rs","byte_start":24731,"byte_end":24764,"line_start":96,"line_end":96,"column_start":28,"column_end":61},"ref_id":{"krate":2,"index":6820}},{"kind":"Type","span":{"file_name":"src/main.rs","byte_start":707,"byte_end":711,"line_start":25,"line_end":25,"column_start":9,"column_end":13},"ref_id":{"krate":2,"index":29812}},{"kind":"Type","span":{"file_name":"src/main.rs","byte_start":707,"byte_end":711,"line_start":25,"line_end":25,"column_start":9,"column_end":13},"ref_id":{"krate":2,"index":29812}},{"kind":"Function","span":{"file_name":"/home/pi/.rustup/toolchains/stable-armv7-unknown-linux-gnueabihf/lib/rustlib/src/rust/library/std/src/macros.rs","byte_start":24731,"byte_end":24764,"line_start":96,"line_end":96,"column_start":28,"column_end":61},"ref_id":{"krate":2,"index":6827}},{"kind":"Variable","span":{"file_name":"src/main.rs","byte_start":754,"byte_end":755,"line_start":28,"line_end":28,"column_start":15,"column_end":16},"ref_id":{"krate":0,"index":3758096387}},{"kind":"Variable","span":{"file_name":"src/main.rs","byte_start":748,"byte_end":749,"line_start":28,"line_end":28,"column_start":9,"column_end":10},"ref_id":{"krate":2,"index":29816}},{"kind":"Function","span":{"file_name":"/home/pi/.rustup/toolchains/stable-armv7-unknown-linux-gnueabihf/lib/rustlib/src/rust/library/std/src/macros.rs","byte_start":24731,"byte_end":24764,"line_start":96,"line_end":96,"column_start":28,"column_end":61},"ref_id":{"krate":2,"index":6827}},{"kind":"Variable","span":{"file_name":"src/main.rs","byte_start":781,"byte_end":782,"line_start":29,"line_end":29,"column_start":24,"column_end":25},"ref_id":{"krate":0,"index":1417674755}},{"kind":"Function","span":{"file_name":"/home/pi/.rustup/toolchains/stable-armv7-unknown-linux-gnueabihf/lib/rustlib/src/rust/library/std/src/macros.rs","byte_start":24731,"byte_end":24764,"line_start":96,"line_end":96,"column_start":28,"column_end":61},"ref_id":{"krate":2,"index":6820}},{"kind":"Function","span":{"file_name":"src/main.rs","byte_start":867,"byte_end":870,"line_start":34,"line_end":34,"column_start":15,"column_end":18},"ref_id":{"krate":5,"index":4889}},{"kind":"Variable","span":{"file_name":"src/main.rs","byte_start":865,"byte_end":866,"line_start":34,"line_end":34,"column_start":13,"column_end":14},"ref_id":{"krate":0,"index":3758096387}},{"kind":"Function","span":{"file_name":"/home/pi/.rustup/toolchains/stable-armv7-unknown-linux-gnueabihf/lib/rustlib/src/rust/library/std/src/macros.rs","byte_start":24731,"byte_end":24764,"line_start":96,"line_end":96,"column_start":28,"column_end":61},"ref_id":{"krate":2,"index":6827}},{"kind":"Variable","span":{"file_name":"src/main.rs","byte_start":924,"byte_end":925,"line_start":35,"line_end":35,"column_start":51,"column_end":52},"ref_id":{"krate":0,"index":1451229187}},{"kind":"Variable","span":{"file_name":"src/main.rs","byte_start":927,"byte_end":928,"line_start":35,"line_end":35,"column_start":54,"column_end":55},"ref_id":{"krate":0,"index":3758096387}},{"kind":"Function","span":{"file_name":"/home/pi/.rustup/toolchains/stable-armv7-unknown-linux-gnueabihf/lib/rustlib/src/rust/library/std/src/macros.rs","byte_start":24731,"byte_end":24764,"line_start":96,"line_end":96,"column_start":28,"column_end":61},"ref_id":{"krate":2,"index":6820}},{"kind":"Function","span":{"file_name":"/home/pi/.rustup/toolchains/stable-armv7-unknown-linux-gnueabihf/lib/rustlib/src/rust/library/std/src/macros.rs","byte_start":24731,"byte_end":24764,"line_start":96,"line_end":96,"column_start":28,"column_end":61},"ref_id":{"krate":2,"index":6820}},{"kind":"Function","span":{"file_name":"src/main.rs","byte_start":958,"byte_end":961,"line_start":37,"line_end":37,"column_start":27,"column_end":30},"ref_id":{"krate":5,"index":4889}},{"kind":"Variable","span":{"file_name":"src/main.rs","byte_start":956,"byte_end":957,"line_start":37,"line_end":37,"column_start":25,"column_end":26},"ref_id":{"krate":0,"index":3758096387}},{"kind":"Type","span":{"file_name":"src/main.rs","byte_start":946,"byte_end":950,"line_start":37,"line_end":37,"column_start":15,"column_end":19},"ref_id":{"krate":2,"index":29814}},{"kind":"Type","span":{"file_name":"src/main.rs","byte_start":946,"byte_end":950,"line_start":37,"line_end":37,"column_start":15,"column_end":19},"ref_id":{"krate":2,"index":29814}},{"kind":"Function","span":{"file_name":"/home/pi/.rustup/toolchains/stable-armv7-unknown-linux-gnueabihf/lib/rustlib/src/rust/library/std/src/macros.rs","byte_start":24731,"byte_end":24764,"line_start":96,"line_end":96,"column_start":28,"column_end":61},"ref_id":{"krate":2,"index":6827}},{"kind":"Variable","span":{"file_name":"src/main.rs","byte_start":992,"byte_end":993,"line_start":38,"line_end":38,"column_start":28,"column_end":29},"ref_id":{"krate":0,"index":3984588803}},{"kind":"Function","span":{"file_name":"/home/pi/.rustup/toolchains/stable-armv7-unknown-linux-gnueabihf/lib/rustlib/src/rust/library/std/src/macros.rs","byte_start":24731,"byte_end":24764,"line_start":96,"line_end":96,"column_start":28,"column_end":61},"ref_id":{"krate":2,"index":6820}},{"kind":"Function","span":{"file_name":"src/main.rs","byte_start":1020,"byte_end":1027,"line_start":44,"line_end":44,"column_start":5,"column_end":12},"ref_id":{"krate":0,"index":3}}],"macro_refs":[],"relations":[]}